pyte/__init__.py
pyte/backports.py
pyte/compiler.py
pyte/exc.py
pyte/superclasses.py
pyte/tokens_32.py
pyte/tokens_33.py
pyte/tokens_34.py
pyte/tokens_35.py
pyte/util.py
pyte/ops/__init__.py
pyte/ops/builders.py
pyte/ops/call.py
pyte/ops/for_.py
pyte/ops/if_.py
pyte/ops/load.py
pyte/ops/store.py
pytec-1.0.0.dist-info/DESCRIPTION.rst
pytec-1.0.0.dist-info/METADATA
pytec-1.0.0.dist-info/RECORD
pytec-1.0.0.dist-info/WHEEL
pytec-1.0.0.dist-info/metadata.json
pytec-1.0.0.dist-info/top_level.txt
