Metadata-Version: 2.0
Name: pytec
Version: 1.0.0
Summary: Pyte bytecode compiler
Home-page: https://github.com/SunDwarf/Pyte
Author: Isaac Dickinson
Author-email: sun@veriny.tf
License: MIT
Platform: UNKNOWN
